{
  "description": "Some Polyhedron",
  "baseFace": {
    "noSides": 4,
    "color": "red" 
  },
  "connections": [
      { "from": 2,  "noSides": 3, "color": "blue",   "fromEdge": [1, 0], "to": 1,  "toEdge": [0, 1] },
      { "from": 3,  "noSides": 3, "color": "green",  "fromEdge": [1, 0], "to": 2,  "toEdge": [2, 0] },
      { "from": 4,  "noSides": 3, "color": "green",  "fromEdge": [1, 0], "to": 1,  "toEdge": [2, 3] },
      { "from": 5,  "noSides": 3, "color": "blue",   "fromEdge": [1, 0], "to": 4,  "toEdge": [2, 0] },
      { "from": 6,  "noSides": 3, "color": "blue",   "fromEdge": [2, 0], "to": 1,  "toEdge": [2, 1] },
      { "from": 7,  "noSides": 3, "color": "yellow", "fromEdge": [1, 0], "to": 6,  "toEdge": [0, 1] },
      { "from": 8,  "noSides": 3, "color": "green",  "fromEdge": [2, 0], "to": 6,  "toEdge": [2, 1] },
      { "from": 9,  "noSides": 3, "color": "yellow", "fromEdge": [1, 0], "to": 8,  "toEdge": [1, 2] },
      { "from": 10, "noSides": 4, "color": "red",    "fromEdge": [0, 3], "to": 8,  "toEdge": [0, 1] },
      { "from": 11, "noSides": 3, "color": "blue",   "fromEdge": [1, 0], "to": 10, "toEdge": [0, 1] },
      { "from": 12, "noSides": 3, "color": "green",  "fromEdge": [1, 0], "to": 11, "toEdge": [2, 0] },
      { "from": 13, "noSides": 3, "color": "green",  "fromEdge": [1, 0], "to": 10, "toEdge": [2, 3] },
      { "from": 14, "noSides": 3, "color": "blue",   "fromEdge": [1, 0], "to": 13, "toEdge": [2, 0] },
      { "from": 15, "noSides": 3, "color": "blue",   "fromEdge": [2, 0], "to": 10, "toEdge": [2, 1] },
      { "from": 16, "noSides": 3, "color": "yellow", "fromEdge": [1, 0], "to": 15, "toEdge": [0, 1] },
      { "from": 17, "noSides": 3, "color": "green",   "fromEdge": [2, 0], "to": 15, "toEdge": [2, 1] },
      { "from": 18, "noSides": 3, "color": "yellow", "fromEdge": [1, 0], "to": 17, "toEdge": [1, 2] },
      { "from": 19, "noSides": 4, "color": "red",    "fromEdge": [0, 3], "to": 17, "toEdge": [0, 1] },
      { "from": 20, "noSides": 3, "color": "blue",   "fromEdge": [1, 0], "to": 19, "toEdge": [0, 1] },
      { "from": 21, "noSides": 3, "color": "green",  "fromEdge": [2, 0], "to": 20, "toEdge": [0, 2] },
      { "from": 22, "noSides": 4, "color": "red",    "fromEdge": [2, 3], "to": 21, "toEdge": [1, 0] },
      { "from": 23, "noSides": 3, "color": "green",  "fromEdge": [1, 0], "to": 19, "toEdge": [2, 3] },
      { "from": 24, "noSides": 3, "color": "blue",   "fromEdge": [1, 0], "to": 23, "toEdge": [2, 0] },
      { "from": 25, "noSides": 4, "color": "red",    "fromEdge": [0, 1], "to": 24, "toEdge": [2, 1] },
      { "from": 26, "noSides": 3, "color": "blue",   "fromEdge": [2, 0], "to": 19, "toEdge": [2, 1] },
      { "from": 27, "noSides": 3, "color": "yellow", "fromEdge": [1, 0], "to": 26, "toEdge": [0, 1] },
      { "from": 28, "noSides": 3, "color": "green",  "fromEdge": [0, 1], "to": 26, "toEdge": [2, 1] },
      { "from": 29, "noSides": 3, "color": "yellow", "fromEdge": [1, 0], "to": 28, "toEdge": [2, 0] },
      { "from": 30, "noSides": 4, "color": "red",    "fromEdge": [0, 3], "to": 28, "toEdge": [1, 2] },
      { "from": 31, "noSides": 3, "color": "green",  "fromEdge": [1, 0], "to": 30, "toEdge": [2, 3] },
      { "from": 32, "noSides": 3, "color": "blue",   "fromEdge": [1, 0], "to": 31, "toEdge": [2, 0] },
      { "from": 33, "noSides": 3, "color": "green",   "fromEdge": [1, 2], "to": 30, "toEdge": [1, 0] },
      { "from": 34, "noSides": 3, "color": "blue",  "fromEdge": [2, 0], "to": 33, "toEdge": [1, 0] },
      { "from": 35, "noSides": 3, "color": "blue",   "fromEdge": [2, 0], "to": 30, "toEdge": [2, 1] },
      { "from": 36, "noSides": 3, "color": "yellow", "fromEdge": [1, 0], "to": 35, "toEdge": [0, 1] },
      { "from": 37, "noSides": 3, "color": "green",  "fromEdge": [0, 2], "to": 35, "toEdge": [1, 2] },
      { "from": 38, "noSides": 3, "color": "yellow", "fromEdge": [1, 0], "to": 37, "toEdge": [1, 2] }
  ]
}
